odoo10_addon_shopinvader_payment_sips-10.0.2.0.0-py3.8-nspkg.pth
odoo/addons/shopinvader_payment_sips/README.rst
odoo/addons/shopinvader_payment_sips/__init__.py
odoo/addons/shopinvader_payment_sips/__manifest__.py
odoo/addons/shopinvader_payment_sips/readme/CONTRIBUTORS.rst
odoo/addons/shopinvader_payment_sips/readme/DESCRIPTION.rst
odoo/addons/shopinvader_payment_sips/services/__init__.py
odoo/addons/shopinvader_payment_sips/services/payment_sips.py
odoo/addons/shopinvader_payment_sips/static/description/index.html
odoo10_addon_shopinvader_payment_sips-10.0.2.0.0.dist-info/METADATA
odoo10_addon_shopinvader_payment_sips-10.0.2.0.0.dist-info/WHEEL
odoo10_addon_shopinvader_payment_sips-10.0.2.0.0.dist-info/namespace_packages.txt
odoo10_addon_shopinvader_payment_sips-10.0.2.0.0.dist-info/top_level.txt
odoo10_addon_shopinvader_payment_sips-10.0.2.0.0.dist-info/RECORD
