Metadata-Version: 2.1
Name: odoo10-addon-shopinvader-payment-sips
Version: 10.0.2.0.0
Summary: Shopinvader REST Services for Worldline SIPS Payments
Home-page: https://github.com/shopinvader/odoo-shopinvader-payment
Author: ACSONE SA/NV
License: AGPL-3
Platform: UNKNOWN
Classifier: Programming Language :: Python
Classifier: Framework :: Odoo
Classifier: License :: OSI Approved :: GNU Affero General Public License v3
Requires-Python: ~=2.7
Requires-Dist: odoo10-addon-invader-payment-sips
Requires-Dist: odoo10-addon-shopinvader-payment
Requires-Dist: odoo (<10.1dev,>=10.0)
